{
  "task": "regresion",
  "target": "punt_sociales_ciudadanas",
  "config": {
    "name": "mlp_64_32",
    "layers": "64-32",
    "activation": "relu",
    "dropout": 0.1,
    "l2": 0.0,
    "optimizer": "adam",
    "learning_rate": 0.001,
    "loss": "mse",
    "epochs": 60,
    "batch_size": 256
  },
  "metrics": {
    "rmse": 9.95624909714158,
    "mae": 7.998833536300699,
    "r2": 0.2488970595745691
  },
  "feature_columns": [
    "cole_naturaleza",
    "fami_estratovivienda",
    "fami_educacionmadre",
    "fami_educacionpadre",
    "cole_area_ubicacion",
    "cole_jornada",
    "fami_tieneinternet",
    "fami_tienecomputador",
    "cole_bilingue",
    "fami_personashogar"
  ],
  "label_mapping": null,
  "trained_at": "2026-05-23 17:09:23"
}